foxInstaller
