Metadata-Version: 1.1
Name: foxInstaller
Version: 0.2.015
Summary: A simple installation script for my own django projects.
Home-page: http://th3f0x.com
Author: Jyrno Ader
Author-email: jyrno42@gmail.com
License: BSD
Keywords: foxInstaller django jyrno42
Platform: UNKNOWN
Classifier: Development Status :: 3 - Alpha
Classifier: Topic :: Utilities
Classifier: License :: OSI Approved :: BSD License
